control_unit/control_unit/control_unit.sv
/* verilator lint_off UNUSED */
module control_unit #(
    parameter DATA_WIDTH = 32
)(
    input   logic   [DATA_WIDTH-1:0]    instr,
    input   logic                       EQ,
    output  logic                       RegWrite,
    output  logic   [2:0]               ALUctrl,
    output  logic                       ALUsrc,
    output  logic   [11:0]              ImmSrc,
    output  logic                       PCsrc
);

    always_comb
        case ({instr[6:0],instr[14:12]})
            {7'b0010011, 3'b000}:   RegWrite = 1'b1;
            default: RegWrite = 1'b0;
        endcase

    always_comb
        case ({instr[6:0],instr[14:12]})
            {7'b0010011, 3'b000}:   ALUctrl = 3'b0;
            default: ALUctrl = 3'b111;
        endcase

    always_comb
        case ({instr[6:0],instr[14:12]})
            {7'b0010011, 3'b000}:   ALUsrc = 1'b1;
            default: ALUsrc = 1'b0;
        endcase

    always_comb
        begin
            if ({instr[6:0],instr[14:12]} == {7'b0010011, 3'b000})
                ImmSrc = {instr[31:20]};
            else if ({instr[6:0],instr[14:12]} == {7'b1100011,3'b001})
                ImmSrc = {instr[31],instr[7],instr[30:25],instr[11:8]};
            else
                ImmSrc = {instr[31:20]};
        end

    always_comb
        begin
            if (({instr[6:0],instr[14:12]} == {7'b1100011,3'b000}) && EQ)
                PCsrc = 1'b1;
            else if (({instr[6:0],instr[14:12]} == {7'b1100011,3'b001}) && ~EQ)
                PCsrc = 1'b1;
            else
                PCsrc = 1'b0;
        end

            

 
endmodule

control_unit/control_unit/control_unit.vcd
$version Generated by VerilatedVcd $end
$date Sun Nov 20 16:19:14 2022 $end
$timescale 1ps $end

 $scope module TOP $end
  $var wire  3 & ALUctrl [2:0] $end
  $var wire  1 ' ALUsrc $end
  $var wire  1 $ EQ $end
  $var wire 12 ( ImmSrc [11:0] $end
  $var wire  1 ) PCsrc $end
  $var wire  1 % RegWrite $end
  $var wire 32 # instr [31:0] $end
  $scope module control_unit $end
   $var wire  3 & ALUctrl [2:0] $end
   $var wire  1 ' ALUsrc $end
   $var wire 32 * DATA_WIDTH [31:0] $end
   $var wire  1 $ EQ $end
   $var wire 12 ( ImmSrc [11:0] $end
   $var wire  1 ) PCsrc $end
   $var wire  1 % RegWrite $end
   $var wire 32 # instr [31:0] $end
  $upscope $end
 $upscope $end
$enddefinitions $end


#0
b11111110000000110001100011100011 #
0$
0%
b000 &
0'
b000000000000 (
0)
b00000000000000000000000000100000 *
#2
b00001111111100000000001100010011 #
b111 &
b111111111000 (
1)
#4
1%
b000 &
1'
b000011111111 (
0)
#6
b00000000000000000000010100010011 #
#8
b000000000000 (
#10
b11111110011001011001110011100011 #
#12
0%
b111 &
0'
b111111111100 (
1)
#14
b00000000000001011000010100010011 #
#16
1%
b000 &
1'
b000000000000 (
0)
#18
b00000000000101011000010110010011 #
#20
b000000000001 (
#22
b11111110011001011001110011100011 #
1$
#24
0%
b111 &
0'
b111111111100 (
