control_unit/sign_extend/sign_extend.sv
/* verilator lint_off UNUSED */
module sign_extend #(
    parameter   DATA_WIDTH = 32,
                IMM_WIDTH = 12
)(
    input   logic [DATA_WIDTH-1:0]  instr,
    input   logic [IMM_WIDTH-1:0]   ImmSrc,    
    output  logic [DATA_WIDTH-1:0]  ImmOp
);

    always_comb 
    
            case ({instr[6:0],instr[14:12],ImmSrc[11]})
                {7'b0010011, 3'b000, 1'b1}:     ImmOp = {20'b11111111111111111111, ImmSrc};
                default:                        ImmOp = {20'b0, ImmSrc};
            endcase
    
    /*
        begin
            if (({instr[6:0],instr[14:12]} == 10'b0010011000) && (ImmSrc[11] == 1'b1))
                ImmOp = {20'b11111111111111111111, ImmSrc};
            else
                ImmOp = {20'b0, ImmSrc};
        end
    */

endmodule

control_unit/sign_extend/sign_extend.vcd
$version Generated by VerilatedVcd $end
$date Sat Nov 19 22:53:27 2022 $end
$timescale 1ps $end

 $scope module TOP $end
  $var wire 32 % ImmOp [31:0] $end
  $var wire 12 $ ImmSrc [11:0] $end
  $var wire 32 # instr [31:0] $end
  $scope module sign_extend $end
   $var wire 32 & DATA_WIDTH [31:0] $end
   $var wire 32 ' IMM_WIDTH [31:0] $end
   $var wire 32 % ImmOp [31:0] $end
   $var wire 12 $ ImmSrc [11:0] $end
   $var wire 32 # instr [31:0] $end
  $upscope $end
 $upscope $end
$enddefinitions $end


#0
b11111110000000110001100011100011 #
b111111111111 $
b00000000000000000000000000000000 %
b00000000000000000000000000100000 &
b00000000000000000000000000001100 '
#2
b00001111111100000000001100010011 #
b00000000000000000000111111111111 %
#4
b11111111111111111111111111111111 %
#6
b00000000000000000000010100010011 #
#8
#10
b00000000000000000000010110010011 #
#12
#14
b00000000000001011000010100010011 #
#16
#18
b00000000000101011000010110010011 #
#20
#22
b11111110011001011001110011100011 #
#24
b00000000000000000000111111111111 %
